type_bridge/__init__.py
type_bridge/query.py
type_bridge/reserved_words.py
type_bridge/session.py
type_bridge/typedb_driver.py
type_bridge/validation.py
type_bridge/attribute/__init__.py
type_bridge/attribute/base.py
type_bridge/attribute/boolean.py
type_bridge/attribute/date.py
type_bridge/attribute/datetime.py
type_bridge/attribute/datetimetz.py
type_bridge/attribute/decimal.py
type_bridge/attribute/double.py
type_bridge/attribute/duration.py
type_bridge/attribute/flags.py
type_bridge/attribute/integer.py
type_bridge/attribute/string.py
type_bridge/crud/__init__.py
type_bridge/crud/base.py
type_bridge/crud/exceptions.py
type_bridge/crud/utils.py
type_bridge/crud/entity/__init__.py
type_bridge/crud/entity/group_by.py
type_bridge/crud/entity/manager.py
type_bridge/crud/entity/query.py
type_bridge/crud/relation/__init__.py
type_bridge/crud/relation/group_by.py
type_bridge/crud/relation/lookup.py
type_bridge/crud/relation/manager.py
type_bridge/crud/relation/query.py
type_bridge/expressions/__init__.py
type_bridge/expressions/aggregate.py
type_bridge/expressions/base.py
type_bridge/expressions/boolean.py
type_bridge/expressions/builtin.py
type_bridge/expressions/comparison.py
type_bridge/expressions/functions.py
type_bridge/expressions/iid.py
type_bridge/expressions/role_player.py
type_bridge/expressions/string.py
type_bridge/fields/__init__.py
type_bridge/fields/base.py
type_bridge/fields/role.py
type_bridge/generator/__init__.py
type_bridge/generator/__main__.py
type_bridge/generator/annotations.py
type_bridge/generator/models.py
type_bridge/generator/naming.py
type_bridge/generator/parser.py
type_bridge/generator/typeql.lark
type_bridge/generator/typeql.pest
type_bridge/generator/render/__init__.py
type_bridge/generator/render/attributes.py
type_bridge/generator/render/entities.py
type_bridge/generator/render/functions.py
type_bridge/generator/render/package.py
type_bridge/generator/render/registry.py
type_bridge/generator/render/relations.py
type_bridge-1.2.6.dist-info/METADATA
type_bridge-1.2.6.dist-info/WHEEL
type_bridge-1.2.6.dist-info/entry_points.txt
type_bridge-1.2.6.dist-info/licenses/LICENSE
type_bridge-1.2.6.dist-info/RECORD
