Metadata-Version: 2.4
Name: type-bridge
Version: 1.2.6
Summary: A modern, Pythonic ORM for TypeDB with an Attribute-based API
Project-URL: Homepage, https://github.com/ds1sqe/type-bridge
Project-URL: Repository, https://github.com/ds1sqe/type-bridge
Project-URL: Documentation, https://github.com/ds1sqe/type-bridge/blob/master/README.md
Project-URL: Issues, https://github.com/ds1sqe/type-bridge/issues
Author-email: ds1sqe <ds1sqe@mensakorea.org>
License: MIT
License-File: LICENSE
Keywords: database,graph-database,orm,typedb,typeql
Classifier: Development Status :: 3 - Alpha
Classifier: Intended Audience :: Developers
Classifier: License :: OSI Approved :: MIT License
Classifier: Programming Language :: Python :: 3
Classifier: Programming Language :: Python :: 3.13
Classifier: Topic :: Database
Classifier: Topic :: Software Development :: Libraries :: Python Modules
Requires-Python: >=3.13
Requires-Dist: isodate==0.7.2
Requires-Dist: jinja2>=3.1.0
Requires-Dist: lark>=1.1.9
Requires-Dist: pydantic>=2.12.4
Requires-Dist: typedb-driver>=3.7.0
Requires-Dist: typer>=0.15.0
Provides-Extra: dev
Requires-Dist: pyright>=1.1.407; extra == 'dev'
Requires-Dist: pytest-asyncio>=1.3.0; extra == 'dev'
Requires-Dist: pytest-order>=1.2.0; extra == 'dev'
Requires-Dist: pytest>=9.0.1; extra == 'dev'
Requires-Dist: ruff>=0.14.5; extra == 'dev'
